{
  "db_name": "PostgreSQL",
  "query": "\n                            WITH prev AS (\n                                SELECT id, state AS old_state, batch_id\n                                FROM requests\n                                WHERE id = $1 AND attempt_id IS NULL\n                                FOR UPDATE\n                            ),\n                            upd AS (\n                                UPDATE requests r SET\n                                    state = 'completed',\n                                    response_status = $2,\n                                    response_body = $3,\n                                    claimed_at = $4,\n                                    started_at = $5,\n                                    completed_at = $6,\n                                    response_size = $7,\n                                    routed_model = $8,\n                                    canceled_at = NULL,\n                                    daemon_id = NULL,\n                                    attempt_id = NULL\n                                FROM prev\n                                WHERE r.id = prev.id\n                                  AND r.state NOT IN ('completed', 'failed')\n                                RETURNING prev.old_state, prev.batch_id\n                            ),\n                            counter_fix AS (\n                                UPDATE batches b SET\n                                    canceled_requests = b.canceled_requests - 1,\n                                    completed_requests = b.completed_requests + 1\n                                FROM upd\n                                WHERE upd.old_state = 'canceled'\n                                  AND b.id = upd.batch_id\n                                  AND b.counts_frozen_at IS NOT NULL\n                            )\n                            SELECT old_state AS \"old_state!\" FROM upd\n                            ",
  "describe": {
    "columns": [
      {
        "ordinal": 0,
        "name": "old_state!",
        "type_info": "Text"
      }
    ],
    "parameters": {
      "Left": [
        "Uuid",
        "Int2",
        "Text",
        "Timestamptz",
        "Timestamptz",
        "Timestamptz",
        "Int8",
        "Text"
      ]
    },
    "nullable": [
      false
    ]
  },
  "hash": "c7722e5c2b3a6f37594a903dae2536cbbf3898a9acc08081ecd4b84909dbf91d"
}
