{
  "db_name": "PostgreSQL",
  "query": "\n                    UPDATE requests SET\n                        state = 'pending',\n                        retry_attempt = $2,\n                        not_before = $3,\n                        daemon_id = NULL,\n                        claimed_at = NULL,\n                        started_at = NULL\n                    WHERE id = $1\n                    ",
  "describe": {
    "columns": [],
    "parameters": {
      "Left": [
        "Uuid",
        "Int4",
        "Timestamptz"
      ]
    },
    "nullable": []
  },
  "hash": "80eefe5251c95128e6806f621a16d87bccf7acd6e0c88644bc98160d050d95d6"
}
